{
    "experiment_name": "ufet_get_embed_bert_large_cnet_prop_vocab_cnetp_pretrained",
    "log_dirctory": "ufet_exp",
    "dataset_params": {
        "dataset_name": "bert_large_cnet_vocab",
        "train_file_path": null,
        "val_file_path": null,
        "test_file_path": null,
        "hf_tokenizer_name": "bert-large-uncased",
        "hf_tokenizer_path": "/scratch/c.scmag3/hf_pretrained_models/bert_large_uncased/tokenizer",
        "concept_max_len": 32,
        "property_max_len": 32,
        "add_context": true,
        "context_num": 6,
        "loader_params": {
            "batch_size": 1024,
            "num_workers": 4,
            "pin_memory": true
        }
    },
    "model_params": {
        "model_name": null,
        "hf_checkpoint_name": "bert-large-uncased",
        "hf_model_path": "/scratch/c.scmag3/hf_pretrained_models/bert_large_uncased/model",
        "vector_strategy": "mask_token"
    },
    "inference_params": {
        "pretrained_model_path": "trained_models/bienc_cnetp_pretrained/bienc_bert_large_cnetp_pretrain_lr26.pt",
        "get_con_prop_embeds": true,
        "input_data_type": "property",
        "concept_file": null,
        "property_file": "/scratch/c.scmag3/ufet_prop_vocab_creation/conceptnet_prop_vocab/cnet_property_vocab_cutoff_3.txt",
        "concept_property_file": null,
        "save_dir": "data/ufet/embeddings",
        "get_con_sim_vocab_properties": false,
        "num_nearest_neighbours": null,
        "concept_embed_pkl": null,
        "get_predict_prop_similar_props": false,
        "num_prop_conjuct": null,
        "pretrain_data": false,
        "pretrain_train_file": null,
        "pretrain_valid_file": null,
        "save_prefix": null,
        "finetune_data": false,
        "split_type": null,
        "fold_file_base_path": null,
        "concept_similar_prop_file": null,
        "vocab_property_embed_pkl": null,
        "predict_property_embed_pkl": null,
        "con_only_similar_data": false,
        "top_k_sim_props": null
    }
}